setup.py
X1X/X1X.py
X1X/__init__.py
X1X.egg-info/PKG-INFO
X1X.egg-info/SOURCES.txt
X1X.egg-info/dependency_links.txt
X1X.egg-info/top_level.txt